[{"question": "Find the third derivative of -8027*c**4 - 2*c**3*m**3 - 2*c**2 + 4759*m**3 wrt c.", "answer": "-192648*c - 12*m**3"}, {"question": "What is the third derivative of -36*h**3*v**3 + 3*h**3*v**2 - 2*h**2*v**3 + 2*h*v**2 wrt v?", "answer": "-216*h**3 - 12*h**2"}, {"question": "What is the third derivative of -s**4 + 913*s**3 + s**2 - s + 55?", "answer": "5478 - 24*s"}, {"question": "Let i(u) be the third derivative of -1/210*u**7 + 0*u**5 - 5*u**2 + 0*u**6 + 0*u + 0*u**3 + 1/8*u**4 + 0. Find the second derivative of i(v) wrt v.", "answer": "-12*v**2"}, {"question": "Let u(o) be the first derivative of -1/4*o**4 + 0*o - o**2 + 0*o**3 + 1. Find the second derivative of u(q) wrt q.", "answer": "-6*q"}, {"question": "Find the second derivative of 2*n - 3*n + 3*n**4 - n**4 - 3*n**4 wrt n.", "answer": "-12*n**2"}, {"question": "What is the third derivative of 976215*z**5 - 1336122*z**2 wrt z?", "answer": "58572900*z**2"}, {"question": "Find the second derivative of 85759*k**4 + 15028*k.", "answer": "1029108*k**2"}, {"question": "What is the derivative of -1438242*x**2 + 2*x + 4733764 wrt x?", "answer": "2 - 2876484*x"}, {"question": "Let p(c) = 7*c**3 + 4*c**2 - 2*c + 181. Let r(s) = -13*s**3 - 7*s**2 + 3*s - 362. Let k(i) = 7*p(i) + 4*r(i). Find the first derivative of k(q) wrt q.", "answer": "-9*q**2 - 2"}, {"question": "Let d(t) be the second derivative of 161*t**6/15 + 517*t**2/2 + 501*t. Differentiate d(k) wrt k.", "answer": "1288*k**3"}, {"question": "Differentiate 3*o - 20 - 14 + 2*o**4 + 14*o + 6*o wrt o.", "answer": "8*o**3 + 23"}]